<zahtev izdavac="Zavod za intelektualnu svojinu" oznaka="z-1">
    <podnosilac redni_broj="1">
        <ime></ime>
        <adresa>
            <ulica></ulica>
            <broj></broj>
            <mesto></mesto>
            <zip></zip>
            <drzava></drzava>
        </adresa>
        <telefon></telefon>
        <email></email>
        <faks></faks>
    </podnosilac>

    <punomocnik redni_broj="2">
        <ime></ime>
        <adresa>
            <ulica></ulica>
            <broj></broj>
            <mesto></mesto>
            <zip></zip>
            <drzava></drzava>
        </adresa>
        <telefon></telefon>
        <email></email>
        <faks></faks>
    </punomocnik>

    <zajednicki_predstavink redni_broj="3">
        <ime></ime>
        <adresa>
            <ulica></ulica>
            <broj></broj>
            <mesto></mesto>
            <zip></zip>
            <drzava></drzava>
        </adresa>
        <telefon></telefon>
        <email></email>
        <faks></faks>
    </zajednicki_predstavink>

    <predmet_prijave redni_broj="4">
        <vrsta_ziga oznaka="a"></vrsta_ziga> <!-- -->
        <format_znaka oznaka="b"></format_znaka> <!-- -->
        <izgled_znaka oznaka="v"></izgled_znaka> <!-- link do slike (?)-->
    </predmet_prijave>

    <boje redni_broj="5">
        <boja>
            <ime></ime>
            <oznaka tip="hex"></oznaka>
        </boja>
    </boje>

    <transliteracija redni_broj="6"></transliteracija>
    
    <prevod redni_broj="7"></prevod>

    <opis redni_broj="8"></opis>

    <klase redni_broj="9">
        <cekirana_klasa></cekirana_klasa> 
    </klase>

    <pravo_prvenstva redni_broj="10"></pravo_prvenstva>

    <placene_takse redni_broj="11">
        <osnovna_taksa oznaka="a"></osnovna_taksa>
        <za_klase broj_klasa=""></za_klase>
        <za_graficko_resenje></za_graficko_resenje>
        <ukupno></ukupno>
        <potpis_podnosioca></potpis_podnosioca>
    </placene_takse>

    <zavod>
        <prilozi>
            <primerak_znaka></primerak_znaka>
            <spisak_robe_i_usluga></spisak_robe_i_usluga>
            <punomocje></punomocje>
            <punomocje_ranije_prilozeno></punomocje_ranije_prilozeno>
            <punomocje_naknadno></punomocje_naknadno>
            <opsti_akt></opsti_akt>
            <dokaz_o_pravu_prvenstva></dokaz_o_pravu_prvenstva>
            <dokaz_o_uplati_takse></dokaz_o_uplati_takse>
        </prilozi>

        <broj_prijave>
            <deo1></deo1>
            <deo2></deo2>
        </broj_prijave>

        <datum_podnosenja>
            <dan></dan>
            <mesec></mesec>
            <godina></godina>
        </datum_podnosenja>
    </zavod>
</zahtev>